hackerforms/__init__.py
hackerforms/actions.py
hackerforms/auth.py
hackerforms/debug_utils.py
hackerforms/environments.py
hackerforms/exit_hook.py
hackerforms/list_item_schema.py
hackerforms/overloads.py
hackerforms/page.py
hackerforms/page_response.py
hackerforms/reactive.py
hackerforms/socket.py
hackerforms/step.py
hackerforms/utils.py
hackerforms/version.py
hackerforms/connection/__init__.py
hackerforms/generated/__init__.py
hackerforms/generated/inputs.py
hackerforms/generated/outputs.py
hackerforms/generated/widget_schema.py
hackerforms-0.28.0.dist-info/METADATA
hackerforms-0.28.0.dist-info/WHEEL
hackerforms-0.28.0.dist-info/top_level.txt
hackerforms-0.28.0.dist-info/RECORD
