Metadata-Version: 2.1
Name: hackerforms
Version: 0.28.0
Summary: Hacker Forms
Home-page: https://github.com/abstra-app/hackerforms-lib
License: MIT
Platform: UNKNOWN
Requires-Dist: setuptools
Requires-Dist: requests
Requires-Dist: websocket-client
Requires-Dist: abstra (==1.2.7)
